[
  {
    "codigoProducto": "01",
    "nombreProducto": "PANTALON",
    "inventarioProducto": 5,
    "precioProducto": 45000
  },
  {
    "codigoProducto": "02",
    "nombreProducto": "CAMISA",
    "inventarioProducto": 6,
    "precioProducto": 15000
  },
  {
    "codigoProducto": "03",
    "nombreProducto": "MEDIAS",
    "inventarioProducto": 23,
    "precioProducto": 1000
  },
  {
    "codigoProducto": "04",
    "nombreProducto": "CHAQUETA",
    "inventarioProducto": 1,
    "precioProducto": 35000
  },
  {
    "codigoProducto": "05",
    "nombreProducto": "ZAPATOS",
    "inventarioProducto": 6,
    "precioProducto": 75000
  },
  {
    "codigoProducto": "86",
    "nombreProducto": "TENIS",
    "inventarioProducto": 14,
    "precioProducto": 65500
  },
  {
    "codigoProducto": "07",
    "nombreProducto": "CELULAR",
    "inventarioProducto": 11,
    "precioProducto": 655000
  }
]